python_console_menu/__init__.py
python_console_menu/python_console_menu.py
python_console_menu-1.1.0.dist-info/LICENSE
python_console_menu-1.1.0.dist-info/METADATA
python_console_menu-1.1.0.dist-info/WHEEL
python_console_menu-1.1.0.dist-info/top_level.txt
python_console_menu-1.1.0.dist-info/RECORD
