Metadata-Version: 2.1
Name: python-console-menu
Version: 1.1.0
Summary: A simple library to handle the menus for your python console applications.
Home-page: https://github.com/lukewarlow/python_console_menu
Author: Luke Warlow
Author-email: projects@warlow.dev
License: UNKNOWN
Keywords: console menu,menu,console
Platform: UNKNOWN
Classifier: Development Status :: 5 - Production/Stable
Classifier: Programming Language :: Python :: 3
Classifier: License :: OSI Approved :: Apache Software License
Classifier: Operating System :: OS Independent
